dataclass2PySide6/__init__.py
dataclass2PySide6/dataclass_widget.py
dataclass2PySide6/datawidgets.py
dataclass2PySide6/py.typed
dataclass2PySide6/typing.py
dataclass2PySide6/version.py
dataclass2PySide6/tests/__init__.py
dataclass2PySide6/tests/test_dataclass_widget.py
dataclass2PySide6/tests/test_datawidgets.py
dataclass2PySide6-1.8.4.dist-info/LICENSE.txt
dataclass2PySide6-1.8.4.dist-info/METADATA
dataclass2PySide6-1.8.4.dist-info/WHEEL
dataclass2PySide6-1.8.4.dist-info/top_level.txt
dataclass2PySide6-1.8.4.dist-info/RECORD
