Metadata-Version: 2.1
Name: dataclass2PySide6
Version: 1.8.4
Summary: Package to construct PySide6 widgets from dataclass
Home-page: https://github.com/JSS95/dataclass2PySide6
Author: Jisoo Song
Author-email: jeesoo9595@snu.ac.kr
Maintainer: Jisoo Song
Maintainer-email: jeesoo9595@snu.ac.kr
License: LGPL
Keywords: GUI
Classifier: Development Status :: 7 - Inactive
Classifier: License :: OSI Approved :: GNU Library or Lesser General Public License (LGPL)
Classifier: Operating System :: MacOS
Classifier: Operating System :: Microsoft :: Windows
Classifier: Operating System :: POSIX
Classifier: Operating System :: Unix
Classifier: Programming Language :: Python :: 3
Classifier: Programming Language :: Python :: 3 :: Only
Classifier: Programming Language :: Python :: 3.9
Classifier: Programming Language :: Python :: 3.10
Requires-Python: >=3.9
License-File: LICENSE.txt
Requires-Dist: PySide6 (!=6.2.2,!=6.2.2.1)
Provides-Extra: full
Requires-Dist: pytest-qt ; extra == 'full'
Requires-Dist: mypy ; extra == 'full'
Requires-Dist: pytest-xvfb ; extra == 'full'
Requires-Dist: flake8 ; extra == 'full'
Requires-Dist: black ; extra == 'full'
Requires-Dist: pytest ; extra == 'full'
Provides-Extra: test
Requires-Dist: black ; extra == 'test'
Requires-Dist: flake8 ; extra == 'test'
Requires-Dist: mypy ; extra == 'test'
Requires-Dist: pytest ; extra == 'test'
Requires-Dist: pytest-qt ; extra == 'test'
Provides-Extra: test-ci
Requires-Dist: black ; extra == 'test-ci'
Requires-Dist: flake8 ; extra == 'test-ci'
Requires-Dist: mypy ; extra == 'test-ci'
Requires-Dist: pytest ; extra == 'test-ci'
Requires-Dist: pytest-qt ; extra == 'test-ci'
Requires-Dist: pytest-xvfb ; extra == 'test-ci'
